CHANGES.txt
CONTRIBUTORS.txt
LICENSE
MANIFEST.in
README.txt
setup.py
docs/LICENSE.GPL
docs/LICENSE.txt
src/ngi/__init__.py
src/ngi.notify.datadog.egg-info/PKG-INFO
src/ngi.notify.datadog.egg-info/SOURCES.txt
src/ngi.notify.datadog.egg-info/dependency_links.txt
src/ngi.notify.datadog.egg-info/entry_points.txt
src/ngi.notify.datadog.egg-info/namespace_packages.txt
src/ngi.notify.datadog.egg-info/not-zip-safe
src/ngi.notify.datadog.egg-info/requires.txt
src/ngi.notify.datadog.egg-info/top_level.txt
src/ngi/notify/__init__.py
src/ngi/notify/datadog/__init__.py
src/ngi/notify/datadog/configure.zcml
src/ngi/notify/datadog/controlpanel.py
src/ngi/notify/datadog/controlpanel.zcml
src/ngi/notify/datadog/dd.py
src/ngi/notify/datadog/events.py
src/ngi/notify/datadog/testing.py
src/ngi/notify/datadog/testing.zcml
src/ngi/notify/datadog/browser/__init__.py
src/ngi/notify/datadog/browser/configure.zcml
src/ngi/notify/datadog/browser/cron_dd.py
src/ngi/notify/datadog/locales/readme.txt
src/ngi/notify/datadog/profiles/default/controlpanel.xml
src/ngi/notify/datadog/profiles/default/metadata.xml
src/ngi/notify/datadog/profiles/default/registry.xml
src/ngi/notify/datadog/static/icon.gif
src/ngi/notify/datadog/tests/__init__.py
src/ngi/notify/datadog/tests/test_setup.py