Metadata-Version: 1.1
Name: ngi.notify.datadog
Version: 1.0b2
Summary: Notify the Plone operation event to the DataDog
Home-page: https://github.com/ngi644/ngi.notify.datadog
Author: Takashi NAGAI
Author-email: ngi644@gmail.com
License: gpl
Platform: UNKNOWN
Classifier: Environment :: Web Environment
Classifier: Framework :: Plone
Classifier: Operating System :: OS Independent
Classifier: Programming Language :: Python
Classifier: Programming Language :: Python :: 2.6
Classifier: Topic :: Software Development :: Libraries :: Python Modules
